djmailer/__init__.py
djmailer/apps.py
djmailer/backend.py
djmailer/tasks.py
djmailer/tests.py
djmailer-0.0.1.dist-info/METADATA
djmailer-0.0.1.dist-info/WHEEL
djmailer-0.0.1.dist-info/licenses/LICENSE
djmailer-0.0.1.dist-info/RECORD
