Metadata-Version: 2.1
Name: djmailer
Version: 0.0.1
Summary: ___
Project-URL: Homepage, https://github.com/neamaddin/djmailer
Project-URL: Bug Tracker, https://github.com/neamaddin/djmailer/issues
Author-email: Neamaddin Akhmedov <neamaddin.a@mail.ru>
License-Expression: MIT
License-File: LICENSE
Classifier: License :: OSI Approved :: MIT License
Classifier: Operating System :: OS Independent
Classifier: Programming Language :: Python :: 3
Requires-Python: >=3.8
Requires-Dist: celery>=5.3
Requires-Dist: django>=3.0
Requires-Dist: mailersend>=0.5.1
Provides-Extra: cov
Requires-Dist: coverage; extra == 'cov'
Provides-Extra: lint
Requires-Dist: pyproject-flake8; extra == 'lint'
Provides-Extra: redis
Requires-Dist: psycopg2-binary>=2.9.6; extra == 'redis'
Requires-Dist: redis>=4.6.0; extra == 'redis'
Provides-Extra: type
Requires-Dist: mypy; extra == 'type'
